README.rst
setup.cfg
setup.py
logging2/__init__.py
logging2/levels.py
logging2/loggers.py
logging2/utils.py
logging2.egg-info/PKG-INFO
logging2.egg-info/SOURCES.txt
logging2.egg-info/dependency_links.txt
logging2.egg-info/requires.txt
logging2.egg-info/top_level.txt