Metadata-Version: 1.1
Name: logging2
Version: 0.1.0
Summary: A More Pythonic Logging System
Home-page: https://github.com/vforgione/logging2
Author: Vince Forgione
Author-email: v.forgione@gmail.com
License: MIT
Keywords: logging
Platform: UNKNOWN
Classifier: Development Status :: 3 - Alpha
Classifier: Intended Audience :: Developers
Classifier: License :: OSI Approved :: MIT License
Classifier: Environment :: Console
Classifier: Environment :: Web Environment
Classifier: Intended Audience :: Developers
Classifier: Intended Audience :: Information Technology
Classifier: Intended Audience :: System Administrators
Classifier: Natural Language :: English
Classifier: Operating System :: MacOS
Classifier: Operating System :: POSIX
Classifier: Programming Language :: Python :: 3.6
